{
  "annotations": { "list": [] },
  "editable": true,
  "fiscalYearStartMonth": 0,
  "graphTooltip": 1,
  "links": [],
  "panels": [
    {
      "title": "Service Health",
      "type": "stat",
      "gridPos": { "h": 4, "w": 24, "x": 0, "y": 0 },
      "targets": [
        {
          "expr": "up",
          "legendFormat": "{{instance}}",
          "refId": "A"
        }
      ],
      "fieldConfig": {
        "defaults": {
          "mappings": [
            { "options": { "0": { "text": "DOWN", "color": "red" } }, "type": "value" },
            { "options": { "1": { "text": "UP", "color": "green" } }, "type": "value" }
          ],
          "thresholds": {
            "mode": "absolute",
            "steps": [
              { "color": "red", "value": null },
              { "color": "green", "value": 1 }
            ]
          }
        },
        "overrides": []
      },
      "options": {
        "reduceOptions": { "calcs": ["lastNotNull"], "fields": "", "values": false },
        "orientation": "horizontal",
        "textMode": "auto",
        "colorMode": "background",
        "graphMode": "none"
      }
    },
    {
      "title": "Process CPU Usage (%)",
      "type": "timeseries",
      "gridPos": { "h": 8, "w": 12, "x": 0, "y": 4 },
      "targets": [
        {
          "expr": "rate(process_cpu_seconds_total{job=\"dotnet-apis\"}[5m]) * 100",
          "legendFormat": "{{instance}}",
          "refId": "A"
        },
        {
          "expr": "rate(process_cpu_seconds_total{job=\"nextjs-webs\"}[5m]) * 100",
          "legendFormat": "{{instance}}",
          "refId": "B"
        }
      ],
      "fieldConfig": {
        "defaults": {
          "unit": "percent",
          "custom": { "drawStyle": "line", "lineWidth": 1, "fillOpacity": 10, "pointSize": 5 }
        }
      }
    },
    {
      "title": "Process Resident Memory",
      "type": "timeseries",
      "gridPos": { "h": 8, "w": 12, "x": 12, "y": 4 },
      "targets": [
        {
          "expr": "process_resident_memory_bytes{job=\"dotnet-apis\"}",
          "legendFormat": "{{instance}}",
          "refId": "A"
        },
        {
          "expr": "process_resident_memory_bytes{job=\"nextjs-webs\"}",
          "legendFormat": "{{instance}}",
          "refId": "B"
        }
      ],
      "fieldConfig": {
        "defaults": {
          "unit": "bytes",
          "custom": { "drawStyle": "line", "lineWidth": 1, "fillOpacity": 10, "pointSize": 5 }
        }
      }
    },
    {
      "title": "Process Virtual Memory",
      "type": "timeseries",
      "gridPos": { "h": 8, "w": 12, "x": 0, "y": 12 },
      "targets": [
        {
          "expr": "process_virtual_memory_bytes{job=\"dotnet-apis\"}",
          "legendFormat": "{{instance}}",
          "refId": "A"
        },
        {
          "expr": "process_virtual_memory_bytes{job=\"nextjs-webs\"}",
          "legendFormat": "{{instance}}",
          "refId": "B"
        }
      ],
      "fieldConfig": {
        "defaults": {
          "unit": "bytes",
          "custom": { "drawStyle": "line", "lineWidth": 1, "fillOpacity": 10, "pointSize": 5 }
        }
      }
    },
    {
      "title": "Process Open File Descriptors",
      "type": "timeseries",
      "gridPos": { "h": 8, "w": 12, "x": 12, "y": 12 },
      "targets": [
        {
          "expr": "process_open_fds{job=\"dotnet-apis\"}",
          "legendFormat": "{{instance}}",
          "refId": "A"
        },
        {
          "expr": "process_open_fds{job=\"nextjs-webs\"}",
          "legendFormat": "{{instance}}",
          "refId": "B"
        }
      ],
      "fieldConfig": {
        "defaults": {
          "custom": { "drawStyle": "line", "lineWidth": 1, "fillOpacity": 10, "pointSize": 5 }
        }
      }
    },
    {
      "title": "Container Total CPU (cAdvisor)",
      "type": "timeseries",
      "gridPos": { "h": 8, "w": 12, "x": 0, "y": 20 },
      "targets": [
        {
          "expr": "rate(container_cpu_usage_seconds_total{id=~\"/docker/.+\"}[5m]) * 100",
          "legendFormat": "{{id}}",
          "refId": "A"
        }
      ],
      "fieldConfig": {
        "defaults": {
          "unit": "percent",
          "custom": { "drawStyle": "line", "lineWidth": 1, "fillOpacity": 10, "pointSize": 5 }
        }
      }
    },
    {
      "title": "Container Total Memory (cAdvisor)",
      "type": "timeseries",
      "gridPos": { "h": 8, "w": 12, "x": 12, "y": 20 },
      "targets": [
        {
          "expr": "container_memory_usage_bytes{id=~\"/docker/.+\"}",
          "legendFormat": "{{id}}",
          "refId": "A"
        }
      ],
      "fieldConfig": {
        "defaults": {
          "unit": "bytes",
          "custom": { "drawStyle": "line", "lineWidth": 1, "fillOpacity": 10, "pointSize": 5 }
        }
      }
    }
  ],
  "schemaVersion": 39,
  "tags": ["infrastructure"],
  "templating": { "list": [] },
  "time": { "from": "now-1h", "to": "now" },
  "title": "Infrastructure - Containers",
  "uid": "altairis-infra"
}
